vdblite/__init__.py
vdblite-0.1.4.dist-info/LICENSE
vdblite-0.1.4.dist-info/METADATA
vdblite-0.1.4.dist-info/WHEEL
vdblite-0.1.4.dist-info/top_level.txt
vdblite-0.1.4.dist-info/RECORD
