Metadata-Version: 2.1
Name: vdblite
Version: 0.1.4
Summary: Vector Database Lite
Home-page: https://github.com/daveshap/VDBLITE
Author: David Shapiro
Author-email: noone@gmail.com
License: MIT
Platform: UNKNOWN
License-File: LICENSE
